CHANGES.txt
LICENSE.txt
README.txt
setup.py
version.txt
raisin/__init__.py
raisin.recipe.load.egg-info/PKG-INFO
raisin.recipe.load.egg-info/SOURCES.txt
raisin.recipe.load.egg-info/dependency_links.txt
raisin.recipe.load.egg-info/entry_points.txt
raisin.recipe.load.egg-info/namespace_packages.txt
raisin.recipe.load.egg-info/not-zip-safe
raisin.recipe.load.egg-info/requires.txt
raisin.recipe.load.egg-info/top_level.txt
raisin/recipe/__init__.py
raisin/recipe/load/__init__.py
raisin/recipe/load/database.py
raisin/recipe/load/tests/README.txt
raisin/recipe/load/tests/__init__.py
raisin/recipe/load/tests/test_recipe.py