Metadata-Version: 1.0
Name: raisin.recipe.load
Version: 1.1.2
Summary: A Buildout recipe for loading data into the Raisin data warehouse
Home-page: http://big.crg.cat/services/grape
Author: Maik Roder
Author-email: maikroeder@gmail.com
License: GPL
Keywords: RNA-Seq pipeline ngs transcriptome bioinformatics ETL
Platform: UNKNOWN
Classifier: Framework :: Buildout
Classifier: Development Status :: 5 - Production/Stable
Classifier: Environment :: Console
Classifier: Programming Language :: Python
Classifier: Intended Audience :: Developers
Classifier: Operating System :: OS Independent
Classifier: License :: OSI Approved :: GNU General Public License (GPL)
Classifier: Natural Language :: English
Classifier: Topic :: Software Development :: Build Tools
Classifier: Topic :: Software Development :: Libraries :: Python Modules
Classifier: Operating System :: POSIX :: Linux
Classifier: Topic :: Scientific/Engineering :: Bio-Informatics
Classifier: Topic :: System :: Installation/Setup
